simple_youtube_api/Channel.py
simple_youtube_api/Comment.py
simple_youtube_api/CommentThread.py
simple_youtube_api/LocalVideo.py
simple_youtube_api/Video.py
simple_youtube_api/YouTube.py
simple_youtube_api/YouTubeVideo.py
simple_youtube_api/__init__.py
simple_youtube_api/decorators.py
simple_youtube_api/name_converter.py
simple_youtube_api/youtube_api.py
simple_youtube_api/youtube_constants.py
simple_youtube_api/data/__init__.py
tests/__init__.py
tests/api_test/__init__.py
tests/api_test/test_channel.py
tests/api_test/test_youtube.py
tests/api_test/test_youtube_video.py
tests/unit_test/__init__.py
tests/unit_test/test_documentation.py
tests/unit_test/test_local_video.py
tests/unit_test/test_youtube_api.py
simple_youtube_api-0.2.8.dist-info/LICENSE.rst
simple_youtube_api-0.2.8.dist-info/METADATA
simple_youtube_api-0.2.8.dist-info/WHEEL
simple_youtube_api-0.2.8.dist-info/top_level.txt
simple_youtube_api-0.2.8.dist-info/RECORD
