Metadata-Version: 2.1
Name: simple-youtube-api
Version: 0.2.8
Summary: A python YouTube API wrapper
Home-page: https://github.com/jonnekaunisto/simple-youtube-api
Author: Jonne Kaunisto
Author-email: jonneka@gmail.com
License: MIT License
Keywords: youtube
Platform: UNKNOWN
Classifier: Development Status :: 2 - Pre-Alpha
Classifier: Intended Audience :: Developers
Classifier: License :: OSI Approved :: MIT License
Classifier: Natural Language :: English
Classifier: Operating System :: OS Independent
Classifier: Programming Language :: Python :: 3 :: Only
Classifier: Topic :: Utilities
Provides-Extra: doc
Provides-Extra: test
